fuzzymap/__init__.py
fuzzymap/fuzzymap.py
fuzzymap-1.1.2.dist-info/LICENSE
fuzzymap-1.1.2.dist-info/METADATA
fuzzymap-1.1.2.dist-info/WHEEL
fuzzymap-1.1.2.dist-info/top_level.txt
fuzzymap-1.1.2.dist-info/RECORD
