Metadata-Version: 2.1
Name: fuzzymap
Version: 1.1.2
Summary: The Fuzzy Map is a polymorph Python dictionary that always returns the value of the closest similar key.
Home-page: https://github.com/pysnippet/fuzzymap
Author: Artyom Vancyan
Author-email: artyom@pysnippet.org
License: GPLv2
Keywords: python,map,dict,match,fuzzy,matching,dictionary,fuzzywuzzy
Platform: unix
Platform: linux
Platform: osx
Platform: win32
Classifier: License :: OSI Approved :: GNU General Public License v2 (GPLv2)
Classifier: Topic :: Software Development :: Libraries :: Python Modules
Classifier: Operating System :: OS Independent
Classifier: Programming Language :: Python :: 3.6
Classifier: Programming Language :: Python :: 3.7
Classifier: Programming Language :: Python :: 3.8
Classifier: Programming Language :: Python :: 3.9
Classifier: Programming Language :: Python :: 3.10
Classifier: Programming Language :: Python :: 3.11
Classifier: Programming Language :: Python :: 3.12
Requires-Python: >=3.6
License-File: LICENSE
Requires-Dist: fuzzywuzzy (>=0.3.0)
Requires-Dist: python-Levenshtein (>=0.12.1)
Provides-Extra: testing
Requires-Dist: pytest (>=6.0) ; extra == 'testing'
Requires-Dist: tox (>=3.24) ; extra == 'testing'
